nichi/__init__.py
nichi/config/__init__.py
nichi/config/config.py
nichi/constants.py
nichi/core/__init__.py
nichi/core/converter.py
nichi/core/files.py
nichi/core/operations.py
nichi/core/organizer.py
nichi/core/parser.py
nichi/core/timing.py
nichi/core/translation.py
nichi/core/translator.py
nichi/exceptions/__init__.py
nichi/main.py
nichi/models/__init__.py
nichi/models/models.py
nichi/services/__init__.py
nichi/services/cache.py
nichi/services/core.py
nichi/services/gemini.py
nichi/services/jellyfin.py
nichi/ui/__init__.py
nichi/ui/components.py
nichi/ui/input.py
nichi/ui/tui.py
nichi/utils/__init__.py
nichi/utils/helpers.py
nichi-2.0.6.dist-info/LICENSE
nichi-2.0.6.dist-info/METADATA
nichi-2.0.6.dist-info/WHEEL
nichi-2.0.6.dist-info/entry_points.txt
nichi-2.0.6.dist-info/RECORD
