Metadata-Version: 2.3
Name: nichi
Version: 2.0.6
Summary: A TUI tool for organizing video files, converting VTT subtitles to SRT format, and translating SRT files using Google Gemini AI.
License: MIT
Keywords: video,subtitles,translation,organization,vtt,srt,gemini
Author: Rafli
Author-email: hidayattul.rafli@gmail.com
Requires-Python: >=3.10,<4.0
Classifier: Development Status :: 4 - Beta
Classifier: Intended Audience :: End Users/Desktop
Classifier: License :: OSI Approved :: MIT License
Classifier: Programming Language :: Python :: 3
Classifier: Programming Language :: Python :: 3.10
Classifier: Programming Language :: Python :: 3.11
Classifier: Programming Language :: Python :: 3.12
Classifier: Programming Language :: Python :: 3.13
Classifier: Topic :: Multimedia :: Video
Classifier: Topic :: Text Processing :: Linguistic
Classifier: Topic :: Utilities
Requires-Dist: google-generativeai (>=0.5.0)
Requires-Dist: markdown-it-py (==4.0.0)
Requires-Dist: mdurl (==0.1.2)
Requires-Dist: pygments (==2.19.2)
Requires-Dist: python-dotenv (==1.0.0)
Requires-Dist: rich (==14.1.0)
Project-URL: Repository, https://github.com/hdytrfli/nichi
